Metadata-Version: 1.0
Name: vk-distributions
Version: 0.1
Summary: Gaussian and Normal distributions
Home-page: UNKNOWN
Author: Vivek Kandasamy
Author-email: vivekkandasmy@yahoo.in
License: UNKNOWN
Platform: UNKNOWN
